[
  {
    "contentKey": "087f648ecf8c7cb9",
    "stock": 22774,
    "stockLevel": "in-stock",
    "price": 0.57,
    "color": {
      "name": "Blue",
      "hex": "#104e8b"
    },
    "imageRefs": [
      30,
      31,
      32,
      33,
      34
    ]
  },
  {
    "contentKey": "19788e185e29c91b",
    "stock": 12462,
    "stockLevel": "in-stock",
    "price": 0.57,
    "color": {
      "name": "Yellow",
      "hex": "#ffcc00"
    },
    "imageRefs": [
      17,
      18,
      19,
      20
    ]
  },
  {
    "contentKey": "48bc6ba5e1752cfe",
    "stock": 7359,
    "stockLevel": "in-stock",
    "price": 0.57,
    "color": {
      "name": "Violet",
      "hex": "#a020f0"
    },
    "imageRefs": [
      40,
      41,
      42,
      43,
      44
    ]
  },
  {
    "contentKey": "5bb72a1b1f0b2c70",
    "stock": 19025,
    "stockLevel": "in-stock",
    "price": 0.57,
    "color": {
      "name": "Red",
      "hex": "#cc0000"
    },
    "imageRefs": [
      9,
      10,
      11,
      12
    ]
  },
  {
    "contentKey": "6c31bdfa3b9cfa46",
    "stock": 24304,
    "stockLevel": "in-stock",
    "price": 0.57,
    "color": {
      "name": "Black",
      "hex": "#000000"
    },
    "imageRefs": [
      5,
      6,
      7,
      8
    ]
  },
  {
    "contentKey": "a4bfcee92c39a873",
    "stock": 8780,
    "stockLevel": "in-stock",
    "price": 0.57,
    "color": {
      "name": "Pink",
      "hex": "#ff34b3"
    },
    "imageRefs": [
      21,
      22,
      23,
      24,
      25,
      26,
      27,
      28,
      29
    ]
  },
  {
    "contentKey": "b9094a81ef5437ac",
    "stock": 6723,
    "stockLevel": "in-stock",
    "price": 0.57,
    "color": {
      "name": "White",
      "hex": "#ffffff"
    },
    "imageRefs": [
      0,
      1,
      2,
      3,
      4
    ]
  },
  {
    "contentKey": "c804974e06782a43",
    "stock": 7010,
    "stockLevel": "in-stock",
    "price": 0.57,
    "color": {
      "name": "Orange",
      "hex": "#ff6600"
    },
    "imageRefs": [
      13,
      14,
      15,
      16
    ]
  },
  {
    "contentKey": "df17920bde557418",
    "stock": 12103,
    "stockLevel": "in-stock",
    "price": 0.57,
    "color": {
      "name": "LIght Green",
      "hex": "#caff70"
    },
    "imageRefs": [
      35,
      36,
      37,
      38,
      39
    ]
  }
]