[
  {
    "contentKey": "07ab4f1a78ae7c9c",
    "stock": 990,
    "stockLevel": "in-stock",
    "price": 8.46,
    "color": {
      "name": "White/Navy",
      "hex": "#ffffff"
    },
    "size": "XL"
  },
  {
    "contentKey": "4e5019756de99753",
    "stock": 1801,
    "stockLevel": "in-stock",
    "price": 8.46,
    "color": {
      "name": "White/Navy",
      "hex": "#ffffff"
    },
    "size": "L"
  },
  {
    "contentKey": "b34648c9225b4586",
    "stock": 518,
    "stockLevel": "in-stock",
    "price": 8.46,
    "color": {
      "name": "White/Navy",
      "hex": "#ffffff"
    },
    "size": "S"
  }
]