[
  {
    "contentKey": "07919b347784832d",
    "stock": 1972,
    "stockLevel": "in-stock",
    "price": 4.98,
    "color": {
      "name": "Light Blue",
      "hex": "#61bbea"
    },
    "size": "L",
    "imageRefs": [
      12,
      13
    ]
  },
  {
    "contentKey": "0b21045df234aaf6",
    "stock": 1566,
    "stockLevel": "in-stock",
    "price": 4.98,
    "color": {
      "name": "Daisy",
      "hex": "#fed141"
    },
    "size": "XL",
    "imageRefs": [
      6,
      7
    ]
  },
  {
    "contentKey": "0d5018056c86261e",
    "stock": 13265,
    "stockLevel": "in-stock",
    "price": 4.98,
    "color": {
      "name": "Navy",
      "hex": "#263147"
    },
    "size": "L",
    "imageRefs": [
      14,
      15
    ]
  },
  {
    "contentKey": "1b3484a0eab10cec",
    "stock": 103,
    "stockLevel": "in-stock",
    "price": 1.5,
    "color": {
      "name": "Bright Salmon",
      "hex": "#e5554f"
    },
    "size": "S",
    "imageRefs": [
      2,
      3
    ]
  },
  {
    "contentKey": "1bc57c7ec05a6ead",
    "stock": 3846,
    "stockLevel": "in-stock",
    "price": 4.98,
    "color": {
      "name": "Royal",
      "hex": "#224d8f"
    },
    "size": "S",
    "imageRefs": [
      22,
      23
    ]
  },
  {
    "contentKey": "1bebe4ec083b4823",
    "stock": 1726,
    "stockLevel": "in-stock",
    "price": 4.98,
    "color": {
      "name": "Light Blue",
      "hex": "#61bbea"
    },
    "imageRefs": [
      12,
      13
    ]
  },
  {
    "contentKey": "1bebe4ec083b4823",
    "stock": 990,
    "stockLevel": "in-stock",
    "price": 7.14,
    "color": {
      "name": "Light Blue",
      "hex": "#61bbea"
    },
    "imageRefs": [
      12,
      13
    ]
  },
  {
    "contentKey": "1d2b0e4d99f60b96",
    "stock": 1712,
    "stockLevel": "in-stock",
    "price": 4.98,
    "color": {
      "name": "Charcoal",
      "hex": "#131313"
    },
    "size": "L",
    "imageRefs": [
      4,
      5
    ]
  },
  {
    "contentKey": "20bfd006333a7317",
    "stock": 3940,
    "stockLevel": "in-stock",
    "price": 4.98,
    "color": {
      "name": "Charcoal",
      "hex": "#131313"
    },
    "size": "XL",
    "imageRefs": [
      4,
      5
    ]
  },
  {
    "contentKey": "296cd31d78f8d433",
    "stock": 4777,
    "stockLevel": "in-stock",
    "price": 4.98,
    "color": {
      "name": "Red",
      "hex": "#b1302a"
    },
    "size": "S",
    "imageRefs": [
      20,
      21
    ]
  },
  {
    "contentKey": "2a22fb1874f7e0b2",
    "stock": 1639,
    "stockLevel": "in-stock",
    "price": 4.98,
    "color": {
      "name": "Sapphire",
      "hex": "#0077b5"
    },
    "size": "L",
    "imageRefs": [
      26,
      27
    ]
  },
  {
    "contentKey": "2c37ad5582817949",
    "stock": 10691,
    "stockLevel": "in-stock",
    "price": 4.98,
    "color": {
      "name": "Royal",
      "hex": "#224d8f"
    },
    "size": "M",
    "imageRefs": [
      22,
      23
    ]
  },
  {
    "contentKey": "2d1152b0c7856d85",
    "stock": 1493,
    "stockLevel": "in-stock",
    "price": 4.98,
    "color": {
      "name": "Light Blue",
      "hex": "#61bbea"
    },
    "size": "M",
    "imageRefs": [
      12,
      13
    ]
  },
  {
    "contentKey": "2d5d09595f5c3450",
    "stock": 7446,
    "stockLevel": "in-stock",
    "price": 4.98,
    "color": {
      "name": "Black",
      "hex": "#1a1718"
    },
    "imageRefs": [
      0,
      1
    ]
  },
  {
    "contentKey": "2d5d09595f5c3450",
    "stock": 7709,
    "stockLevel": "in-stock",
    "price": 7.14,
    "color": {
      "name": "Black",
      "hex": "#1a1718"
    },
    "imageRefs": [
      0,
      1
    ]
  },
  {
    "contentKey": "2d5d09595f5c3450",
    "stock": 2359,
    "stockLevel": "in-stock",
    "price": 7.14,
    "color": {
      "name": "Black",
      "hex": "#1a1718"
    },
    "imageRefs": [
      0,
      1
    ]
  },
  {
    "contentKey": "2f0aa7e089012e62",
    "stock": 3531,
    "stockLevel": "in-stock",
    "price": 4.98,
    "color": {
      "name": "Light Blue",
      "hex": "#61bbea"
    },
    "size": "S",
    "imageRefs": [
      12,
      13
    ]
  },
  {
    "contentKey": "3470fa4d69a0d8e7",
    "stock": 801,
    "stockLevel": "in-stock",
    "price": 1.5,
    "color": {
      "name": "Orange",
      "hex": "#df6426"
    },
    "size": "S",
    "imageRefs": [
      16,
      17
    ]
  },
  {
    "contentKey": "36167b9711c5ac0a",
    "stock": 969,
    "stockLevel": "in-stock",
    "price": 4.98,
    "color": {
      "name": "Sapphire",
      "hex": "#0077b5"
    },
    "size": "S",
    "imageRefs": [
      26,
      27
    ]
  },
  {
    "contentKey": "3a6e5f7ac63b1f8a",
    "stock": 1650,
    "stockLevel": "in-stock",
    "price": 4.98,
    "color": {
      "name": "Daisy",
      "hex": "#fed141"
    },
    "size": "L",
    "imageRefs": [
      6,
      7
    ]
  },
  {
    "contentKey": "3fbd8959c6d56001",
    "stock": 5912,
    "stockLevel": "in-stock",
    "price": 4.98,
    "color": {
      "name": "Navy",
      "hex": "#263147"
    },
    "imageRefs": [
      14,
      15
    ]
  },
  {
    "contentKey": "3fbd8959c6d56001",
    "stock": 2496,
    "stockLevel": "in-stock",
    "price": 7.14,
    "color": {
      "name": "Navy",
      "hex": "#263147"
    },
    "imageRefs": [
      14,
      15
    ]
  },
  {
    "contentKey": "3fbd8959c6d56001",
    "stock": 1699,
    "stockLevel": "in-stock",
    "price": 7.14,
    "color": {
      "name": "Navy",
      "hex": "#263147"
    },
    "imageRefs": [
      14,
      15
    ]
  },
  {
    "contentKey": "434531acdc05dbef",
    "stock": 10178,
    "stockLevel": "in-stock",
    "price": 4.98,
    "color": {
      "name": "Sport Grey",
      "hex": "#a4a4a4"
    },
    "size": "L",
    "imageRefs": [
      28,
      29
    ]
  },
  {
    "contentKey": "45f4bc883f94a641",
    "stock": 1016,
    "stockLevel": "in-stock",
    "price": 4.98,
    "color": {
      "name": "Forest Green",
      "hex": "#273b33"
    },
    "size": "S",
    "imageRefs": [
      8,
      9
    ]
  },
  {
    "contentKey": "476a86cb3050a19d",
    "stock": 18428,
    "stockLevel": "in-stock",
    "price": 4.98,
    "color": {
      "name": "Black",
      "hex": "#1a1718"
    },
    "size": "L",
    "imageRefs": [
      0,
      1
    ]
  },
  {
    "contentKey": "4bec521453a7d263",
    "stock": 1863,
    "stockLevel": "in-stock",
    "price": 4.98,
    "color": {
      "name": "Daisy",
      "hex": "#fed141"
    },
    "size": "S",
    "imageRefs": [
      6,
      7
    ]
  },
  {
    "contentKey": "4fa85de43d83fb8a",
    "stock": 1714,
    "stockLevel": "in-stock",
    "price": 4.98,
    "color": {
      "name": "Sand",
      "hex": "#cabfad"
    },
    "size": "XL",
    "imageRefs": [
      24,
      25
    ]
  },
  {
    "contentKey": "4fc256fa5bfc348f",
    "stock": 7671,
    "stockLevel": "in-stock",
    "price": 4.98,
    "color": {
      "name": "Sport Grey",
      "hex": "#a4a4a4"
    },
    "size": "M",
    "imageRefs": [
      28,
      29
    ]
  },
  {
    "contentKey": "504705e72bf1bc91",
    "stock": 2471,
    "stockLevel": "in-stock",
    "price": 4.98,
    "color": {
      "name": "Sapphire",
      "hex": "#0077b5"
    },
    "size": "XL",
    "imageRefs": [
      26,
      27
    ]
  },
  {
    "contentKey": "50dc2e96865e3ae5",
    "stock": 5591,
    "stockLevel": "in-stock",
    "price": 4.98,
    "color": {
      "name": "Forest Green",
      "hex": "#273b33"
    },
    "size": "M",
    "imageRefs": [
      8,
      9
    ]
  },
  {
    "contentKey": "5aed4a7b0393604e",
    "stock": 6734,
    "stockLevel": "in-stock",
    "price": 4.98,
    "color": {
      "name": "Red",
      "hex": "#b1302a"
    },
    "size": "L",
    "imageRefs": [
      20,
      21
    ]
  },
  {
    "contentKey": "62b04aaadb48353f",
    "stock": 1601,
    "stockLevel": "in-stock",
    "price": 4.98,
    "color": {
      "name": "Charcoal",
      "hex": "#131313"
    },
    "size": "S",
    "imageRefs": [
      4,
      5
    ]
  },
  {
    "contentKey": "62e466cc570dd7cf",
    "stock": 2688,
    "stockLevel": "in-stock",
    "price": 7.14,
    "color": {
      "name": "Forest Green",
      "hex": "#273b33"
    },
    "imageRefs": [
      8,
      9
    ]
  },
  {
    "contentKey": "62e466cc570dd7cf",
    "stock": 480,
    "stockLevel": "in-stock",
    "price": 7.14,
    "color": {
      "name": "Forest Green",
      "hex": "#273b33"
    },
    "imageRefs": [
      8,
      9
    ]
  },
  {
    "contentKey": "65f9cfacd7777e63",
    "stock": 14965,
    "stockLevel": "in-stock",
    "price": 4.11,
    "color": {
      "name": "White",
      "hex": "#ffffff"
    },
    "size": "S",
    "imageRefs": [
      30,
      31
    ]
  },
  {
    "contentKey": "6cc608086d454a78",
    "stock": 711,
    "stockLevel": "in-stock",
    "price": 1.5,
    "color": {
      "name": "Orange",
      "hex": "#df6426"
    },
    "imageRefs": [
      16,
      17
    ]
  },
  {
    "contentKey": "6d32d15a92ddcff4",
    "stock": 10794,
    "stockLevel": "in-stock",
    "price": 4.98,
    "color": {
      "name": "Royal",
      "hex": "#224d8f"
    },
    "size": "L",
    "imageRefs": [
      22,
      23
    ]
  },
  {
    "contentKey": "6ee8b5c49e66ff78",
    "stock": 4436,
    "stockLevel": "in-stock",
    "price": 4.98,
    "color": {
      "name": "Sport Grey",
      "hex": "#a4a4a4"
    },
    "imageRefs": [
      28,
      29
    ]
  },
  {
    "contentKey": "6ee8b5c49e66ff78",
    "stock": 1434,
    "stockLevel": "in-stock",
    "price": 7.14,
    "color": {
      "name": "Sport Grey",
      "hex": "#a4a4a4"
    },
    "imageRefs": [
      28,
      29
    ]
  },
  {
    "contentKey": "6ee8b5c49e66ff78",
    "stock": 2230,
    "stockLevel": "in-stock",
    "price": 7.14,
    "color": {
      "name": "Sport Grey",
      "hex": "#a4a4a4"
    },
    "imageRefs": [
      28,
      29
    ]
  },
  {
    "contentKey": "70dd4df0c8a67aa0",
    "stock": 4537,
    "stockLevel": "in-stock",
    "price": 4.98,
    "color": {
      "name": "Forest Green",
      "hex": "#273b33"
    },
    "size": "L",
    "imageRefs": [
      8,
      9
    ]
  },
  {
    "contentKey": "79759778a4147ff9",
    "stock": 2352,
    "stockLevel": "in-stock",
    "price": 4.98,
    "color": {
      "name": "Sand",
      "hex": "#cabfad"
    },
    "size": "M",
    "imageRefs": [
      24,
      25
    ]
  },
  {
    "contentKey": "7f7d1a57ce71b93e",
    "stock": 4564,
    "stockLevel": "in-stock",
    "price": 4.98,
    "color": {
      "name": "Forest Green",
      "hex": "#273b33"
    },
    "size": "XL",
    "imageRefs": [
      8,
      9
    ]
  },
  {
    "contentKey": "895b31f8bd0215fc",
    "stock": 13457,
    "stockLevel": "in-stock",
    "price": 4.98,
    "color": {
      "name": "Navy",
      "hex": "#263147"
    },
    "size": "M",
    "imageRefs": [
      14,
      15
    ]
  },
  {
    "contentKey": "8c4d0871d15fd3ac",
    "stock": 8503,
    "stockLevel": "in-stock",
    "price": 4.98,
    "color": {
      "name": "Sport Grey",
      "hex": "#a4a4a4"
    },
    "size": "XL",
    "imageRefs": [
      28,
      29
    ]
  },
  {
    "contentKey": "8cbfe7e06452b2da",
    "stock": 18406,
    "stockLevel": "in-stock",
    "price": 4.98,
    "color": {
      "name": "Black",
      "hex": "#1a1718"
    },
    "size": "XL",
    "imageRefs": [
      0,
      1
    ]
  },
  {
    "contentKey": "90d6e9392707021f",
    "stock": 10912,
    "stockLevel": "in-stock",
    "price": 4.98,
    "color": {
      "name": "Royal",
      "hex": "#224d8f"
    },
    "size": "XL",
    "imageRefs": [
      22,
      23
    ]
  },
  {
    "contentKey": "93f9052765ecc5f0",
    "stock": 1571,
    "stockLevel": "in-stock",
    "price": 4.98,
    "color": {
      "name": "Red",
      "hex": "#b1302a"
    },
    "imageRefs": [
      20,
      21
    ]
  },
  {
    "contentKey": "93f9052765ecc5f0",
    "stock": 2263,
    "stockLevel": "in-stock",
    "price": 7.14,
    "color": {
      "name": "Red",
      "hex": "#b1302a"
    },
    "imageRefs": [
      20,
      21
    ]
  },
  {
    "contentKey": "93f9052765ecc5f0",
    "stock": 1713,
    "stockLevel": "in-stock",
    "price": 7.14,
    "color": {
      "name": "Red",
      "hex": "#b1302a"
    },
    "imageRefs": [
      20,
      21
    ]
  },
  {
    "contentKey": "9ba48aef5cb5ae85",
    "stock": 3212,
    "stockLevel": "in-stock",
    "price": 1.98,
    "color": {
      "name": "Orange",
      "hex": "#df6426"
    },
    "size": "M",
    "imageRefs": [
      16,
      17
    ]
  },
  {
    "contentKey": "9d795818d97de272",
    "stock": 742,
    "stockLevel": "in-stock",
    "price": 4.98,
    "color": {
      "name": "Sand",
      "hex": "#cabfad"
    },
    "imageRefs": [
      24,
      25
    ]
  },
  {
    "contentKey": "9d795818d97de272",
    "stock": 1657,
    "stockLevel": "in-stock",
    "price": 7.14,
    "color": {
      "name": "Sand",
      "hex": "#cabfad"
    },
    "imageRefs": [
      24,
      25
    ]
  },
  {
    "contentKey": "9d795818d97de272",
    "stock": 1974,
    "stockLevel": "in-stock",
    "price": 7.14,
    "color": {
      "name": "Sand",
      "hex": "#cabfad"
    },
    "imageRefs": [
      24,
      25
    ]
  },
  {
    "contentKey": "9e13c3eb7546481f",
    "stock": 12029,
    "stockLevel": "in-stock",
    "price": 4.98,
    "color": {
      "name": "Navy",
      "hex": "#263147"
    },
    "size": "XL",
    "imageRefs": [
      14,
      15
    ]
  },
  {
    "contentKey": "a1ece34f2f4de79e",
    "stock": 1012,
    "stockLevel": "in-stock",
    "price": 4.98,
    "color": {
      "name": "Daisy",
      "hex": "#fed141"
    },
    "imageRefs": [
      6,
      7
    ]
  },
  {
    "contentKey": "a1ece34f2f4de79e",
    "stock": 1387,
    "stockLevel": "in-stock",
    "price": 7.14,
    "color": {
      "name": "Daisy",
      "hex": "#fed141"
    },
    "imageRefs": [
      6,
      7
    ]
  },
  {
    "contentKey": "a1ece34f2f4de79e",
    "stock": 1237,
    "stockLevel": "in-stock",
    "price": 7.14,
    "color": {
      "name": "Daisy",
      "hex": "#fed141"
    },
    "imageRefs": [
      6,
      7
    ]
  },
  {
    "contentKey": "a206a6c434fa6240",
    "stock": 657,
    "stockLevel": "in-stock",
    "price": 4.98,
    "color": {
      "name": "Purple",
      "hex": "#3f2a56"
    },
    "size": "S",
    "imageRefs": [
      18,
      19
    ]
  },
  {
    "contentKey": "a5195c9f84d57685",
    "stock": 6632,
    "stockLevel": "in-stock",
    "price": 4.98,
    "color": {
      "name": "Red",
      "hex": "#b1302a"
    },
    "size": "XL",
    "imageRefs": [
      20,
      21
    ]
  },
  {
    "contentKey": "a84882e010c2f584",
    "stock": 179,
    "stockLevel": "in-stock",
    "price": 1.5,
    "color": {
      "name": "Bright Salmon",
      "hex": "#e5554f"
    },
    "size": "L",
    "imageRefs": [
      2,
      3
    ]
  },
  {
    "contentKey": "a9d993f4456f69c9",
    "stock": 24216,
    "stockLevel": "in-stock",
    "price": 4.11,
    "color": {
      "name": "White",
      "hex": "#ffffff"
    },
    "size": "M",
    "imageRefs": [
      30,
      31
    ]
  },
  {
    "contentKey": "aaee169bd663b012",
    "stock": 1058,
    "stockLevel": "in-stock",
    "price": 4.98,
    "color": {
      "name": "Sapphire",
      "hex": "#0077b5"
    },
    "size": "M",
    "imageRefs": [
      26,
      27
    ]
  },
  {
    "contentKey": "ac7d466acc8f150a",
    "stock": 2167,
    "stockLevel": "in-stock",
    "price": 4.98,
    "color": {
      "name": "Light Blue",
      "hex": "#61bbea"
    },
    "size": "XL",
    "imageRefs": [
      12,
      13
    ]
  },
  {
    "contentKey": "b0c5546247392730",
    "stock": 2243,
    "stockLevel": "in-stock",
    "price": 1.98,
    "color": {
      "name": "Orange",
      "hex": "#df6426"
    },
    "size": "L",
    "imageRefs": [
      16,
      17
    ]
  },
  {
    "contentKey": "b168c9e0faeb294b",
    "stock": 7656,
    "stockLevel": "in-stock",
    "price": 4.98,
    "color": {
      "name": "Charcoal",
      "hex": "#131313"
    },
    "size": "M",
    "imageRefs": [
      4,
      5
    ]
  },
  {
    "contentKey": "b2def626caed9e02",
    "stock": 554,
    "stockLevel": "in-stock",
    "price": 4.98,
    "color": {
      "name": "Purple",
      "hex": "#3f2a56"
    },
    "size": "L",
    "imageRefs": [
      18,
      19
    ]
  },
  {
    "contentKey": "b43d88bcaa3d418b",
    "stock": 7685,
    "stockLevel": "in-stock",
    "price": 4.98,
    "color": {
      "name": "Royal",
      "hex": "#224d8f"
    },
    "imageRefs": [
      22,
      23
    ]
  },
  {
    "contentKey": "b43d88bcaa3d418b",
    "stock": 1955,
    "stockLevel": "in-stock",
    "price": 7.14,
    "color": {
      "name": "Royal",
      "hex": "#224d8f"
    },
    "imageRefs": [
      22,
      23
    ]
  },
  {
    "contentKey": "b43d88bcaa3d418b",
    "stock": 1989,
    "stockLevel": "in-stock",
    "price": 7.14,
    "color": {
      "name": "Royal",
      "hex": "#224d8f"
    },
    "imageRefs": [
      22,
      23
    ]
  },
  {
    "contentKey": "c09c39d14f7fa6d6",
    "stock": 7052,
    "stockLevel": "in-stock",
    "price": 4.98,
    "color": {
      "name": "Navy",
      "hex": "#263147"
    },
    "size": "S",
    "imageRefs": [
      14,
      15
    ]
  },
  {
    "contentKey": "c3a0a6c764dc86f7",
    "stock": 6132,
    "stockLevel": "in-stock",
    "price": 4.98,
    "color": {
      "name": "Black",
      "hex": "#1a1718"
    },
    "size": "S",
    "imageRefs": [
      0,
      1
    ]
  },
  {
    "contentKey": "c8cefe81cf498572",
    "stock": 9055,
    "stockLevel": "in-stock",
    "price": 4.11,
    "color": {
      "name": "White",
      "hex": "#ffffff"
    },
    "imageRefs": [
      30,
      31
    ]
  },
  {
    "contentKey": "c8cefe81cf498572",
    "stock": 4572,
    "stockLevel": "in-stock",
    "price": 5.97,
    "color": {
      "name": "White",
      "hex": "#ffffff"
    },
    "imageRefs": [
      30,
      31
    ]
  },
  {
    "contentKey": "c8cefe81cf498572",
    "stock": 4029,
    "stockLevel": "in-stock",
    "price": 5.97,
    "color": {
      "name": "White",
      "hex": "#ffffff"
    },
    "imageRefs": [
      30,
      31
    ]
  },
  {
    "contentKey": "c8d105cffdf87da2",
    "stock": 2282,
    "stockLevel": "in-stock",
    "price": 4.98,
    "color": {
      "name": "Daisy",
      "hex": "#fed141"
    },
    "size": "M",
    "imageRefs": [
      6,
      7
    ]
  },
  {
    "contentKey": "cab20bd5a3806011",
    "stock": 4022,
    "stockLevel": "in-stock",
    "price": 4.98,
    "color": {
      "name": "Purple",
      "hex": "#3f2a56"
    },
    "size": "M",
    "imageRefs": [
      18,
      19
    ]
  },
  {
    "contentKey": "cce1c27ced07d55c",
    "stock": 1073,
    "stockLevel": "in-stock",
    "price": 4.98,
    "color": {
      "name": "Purple",
      "hex": "#3f2a56"
    },
    "imageRefs": [
      18,
      19
    ]
  },
  {
    "contentKey": "cce1c27ced07d55c",
    "stock": 1545,
    "stockLevel": "in-stock",
    "price": 7.14,
    "color": {
      "name": "Purple",
      "hex": "#3f2a56"
    },
    "imageRefs": [
      18,
      19
    ]
  },
  {
    "contentKey": "cce1c27ced07d55c",
    "stock": 1067,
    "stockLevel": "in-stock",
    "price": 7.14,
    "color": {
      "name": "Purple",
      "hex": "#3f2a56"
    },
    "imageRefs": [
      18,
      19
    ]
  },
  {
    "contentKey": "cd512f4776ccaaee",
    "stock": 7928,
    "stockLevel": "in-stock",
    "price": 4.98,
    "color": {
      "name": "Red",
      "hex": "#b1302a"
    },
    "size": "M",
    "imageRefs": [
      20,
      21
    ]
  },
  {
    "contentKey": "d2c8cf551f25c8e7",
    "stock": 2933,
    "stockLevel": "in-stock",
    "price": 4.98,
    "color": {
      "name": "Sport Grey",
      "hex": "#a4a4a4"
    },
    "size": "S",
    "imageRefs": [
      28,
      29
    ]
  },
  {
    "contentKey": "d548a8d95e3a1243",
    "stock": 1673,
    "stockLevel": "in-stock",
    "price": 4.98,
    "color": {
      "name": "Sand",
      "hex": "#cabfad"
    },
    "size": "L",
    "imageRefs": [
      24,
      25
    ]
  },
  {
    "contentKey": "db90e32c7738ddf5",
    "stock": 777,
    "stockLevel": "in-stock",
    "price": 4.98,
    "color": {
      "name": "Sapphire",
      "hex": "#0077b5"
    },
    "imageRefs": [
      26,
      27
    ]
  },
  {
    "contentKey": "db90e32c7738ddf5",
    "stock": 2073,
    "stockLevel": "in-stock",
    "price": 7.14,
    "color": {
      "name": "Sapphire",
      "hex": "#0077b5"
    },
    "imageRefs": [
      26,
      27
    ]
  },
  {
    "contentKey": "db90e32c7738ddf5",
    "stock": 1759,
    "stockLevel": "in-stock",
    "price": 7.14,
    "color": {
      "name": "Sapphire",
      "hex": "#0077b5"
    },
    "imageRefs": [
      26,
      27
    ]
  },
  {
    "contentKey": "de15ebc412eacf27",
    "stock": 18805,
    "stockLevel": "in-stock",
    "price": 4.98,
    "color": {
      "name": "Black",
      "hex": "#1a1718"
    },
    "size": "M",
    "imageRefs": [
      0,
      1
    ]
  },
  {
    "contentKey": "e51e2c3ee2148097",
    "stock": 54,
    "stockLevel": "in-stock",
    "price": 0.84,
    "color": {
      "name": "Heliconia",
      "hex": "#db3e79"
    },
    "imageRefs": [
      10,
      11
    ]
  },
  {
    "contentKey": "ed508f47f2322d1f",
    "stock": 27065,
    "stockLevel": "in-stock",
    "price": 4.11,
    "color": {
      "name": "White",
      "hex": "#ffffff"
    },
    "size": "L",
    "imageRefs": [
      30,
      31
    ]
  },
  {
    "contentKey": "ed5ba2e81a552e3e",
    "stock": 2151,
    "stockLevel": "in-stock",
    "price": 4.98,
    "color": {
      "name": "Charcoal",
      "hex": "#131313"
    },
    "imageRefs": [
      4,
      5
    ]
  },
  {
    "contentKey": "ed5ba2e81a552e3e",
    "stock": 1597,
    "stockLevel": "in-stock",
    "price": 7.14,
    "color": {
      "name": "Charcoal",
      "hex": "#131313"
    },
    "imageRefs": [
      4,
      5
    ]
  },
  {
    "contentKey": "ed5ba2e81a552e3e",
    "stock": 1360,
    "stockLevel": "in-stock",
    "price": 7.14,
    "color": {
      "name": "Charcoal",
      "hex": "#131313"
    },
    "imageRefs": [
      4,
      5
    ]
  },
  {
    "contentKey": "f00a10c4be3befea",
    "stock": 16430,
    "stockLevel": "in-stock",
    "price": 4.11,
    "color": {
      "name": "White",
      "hex": "#ffffff"
    },
    "size": "XL",
    "imageRefs": [
      30,
      31
    ]
  },
  {
    "contentKey": "f5c97457b5a0a6ff",
    "stock": 504,
    "stockLevel": "in-stock",
    "price": 1.5,
    "color": {
      "name": "Bright Salmon",
      "hex": "#e5554f"
    },
    "size": "M",
    "imageRefs": [
      2,
      3
    ]
  },
  {
    "contentKey": "f8c27a330e45d4a3",
    "stock": 4487,
    "stockLevel": "in-stock",
    "price": 4.98,
    "color": {
      "name": "Sand",
      "hex": "#cabfad"
    },
    "size": "S",
    "imageRefs": [
      24,
      25
    ]
  }
]