[
  {
    "contentKey": "3a933086fa15c37f",
    "stock": 6610,
    "stockLevel": "in-stock",
    "price": 2.34,
    "color": {
      "name": "Blue",
      "hex": "#104e8b"
    },
    "imageRefs": [
      15,
      16,
      17,
      18,
      19
    ]
  },
  {
    "contentKey": "4499e2630436dcd0",
    "stock": 9592,
    "stockLevel": "in-stock",
    "price": 2.34,
    "color": {
      "name": "Red",
      "hex": "#cc0000"
    },
    "imageRefs": [
      0,
      1,
      2,
      3,
      4
    ]
  },
  {
    "contentKey": "6eec02ac51e91e0e",
    "stock": 14168,
    "stockLevel": "in-stock",
    "price": 2.34,
    "color": {
      "name": "Grey",
      "hex": "#909090"
    },
    "imageRefs": [
      10,
      11,
      12,
      13,
      14
    ]
  },
  {
    "contentKey": "b5ba94a7c390398e",
    "stock": 13633,
    "stockLevel": "in-stock",
    "price": 2.34,
    "color": {
      "name": "Black",
      "hex": "#000000"
    },
    "imageRefs": [
      20,
      21,
      22,
      23,
      24
    ]
  },
  {
    "contentKey": "ddd9cd11730c4196",
    "stock": 4961,
    "stockLevel": "in-stock",
    "price": 2.34,
    "color": {
      "name": "Green",
      "hex": "#00cc00"
    },
    "imageRefs": [
      5,
      6,
      7,
      8,
      9
    ]
  }
]