[
  {
    "contentKey": "368b05a440ff1ddc",
    "stock": 503,
    "stockLevel": "in-stock",
    "price": 19.9,
    "color": {
      "name": "Olive",
      "hex": "#6b6f58"
    },
    "size": "M",
    "imageRefs": [
      16,
      17,
      18,
      19,
      20,
      21,
      22,
      23
    ]
  },
  {
    "contentKey": "3de69224112b1e45",
    "stock": 438,
    "stockLevel": "in-stock",
    "price": 19.9,
    "color": {
      "name": "Olive",
      "hex": "#6b6f58"
    },
    "size": "L",
    "imageRefs": [
      16,
      17,
      18,
      19,
      20,
      21,
      22,
      23
    ]
  },
  {
    "contentKey": "41d994259ba64c2d",
    "stock": 1034,
    "stockLevel": "in-stock",
    "price": 19.9,
    "color": {
      "name": "French Navy",
      "hex": "#12315a"
    },
    "size": "L",
    "imageRefs": [
      8,
      9,
      10,
      11,
      12,
      13,
      14,
      15
    ]
  },
  {
    "contentKey": "61cf58f18a365cef",
    "stock": 1278,
    "stockLevel": "in-stock",
    "price": 19.9,
    "color": {
      "name": "Black",
      "hex": "#000000"
    },
    "size": "XL",
    "imageRefs": [
      0,
      1,
      2,
      3,
      4,
      5,
      6,
      7
    ]
  },
  {
    "contentKey": "8617cac51544f277",
    "stock": 1260,
    "stockLevel": "in-stock",
    "price": 19.9,
    "color": {
      "name": "Black",
      "hex": "#000000"
    },
    "size": "S",
    "imageRefs": [
      0,
      1,
      2,
      3,
      4,
      5,
      6,
      7
    ]
  },
  {
    "contentKey": "87e1cf0a5de7c6a5",
    "stock": 130,
    "stockLevel": "in-stock",
    "price": 19.9,
    "color": {
      "name": "Olive",
      "hex": "#6b6f58"
    },
    "size": "XL",
    "imageRefs": [
      16,
      17,
      18,
      19,
      20,
      21,
      22,
      23
    ]
  },
  {
    "contentKey": "9357b7c1f6472121",
    "stock": 151,
    "stockLevel": "in-stock",
    "price": 19.9,
    "color": {
      "name": "French Navy",
      "hex": "#12315a"
    },
    "size": "XL",
    "imageRefs": [
      8,
      9,
      10,
      11,
      12,
      13,
      14,
      15
    ]
  },
  {
    "contentKey": "940059e77fe6fda7",
    "stock": 586,
    "stockLevel": "in-stock",
    "price": 19.9,
    "color": {
      "name": "Black",
      "hex": "#000000"
    },
    "imageRefs": [
      0,
      1,
      2,
      3,
      4,
      5,
      6,
      7
    ]
  },
  {
    "contentKey": "c8d9eb0abaabc4c8",
    "stock": 485,
    "stockLevel": "in-stock",
    "price": 19.9,
    "color": {
      "name": "French Navy",
      "hex": "#12315a"
    },
    "size": "S",
    "imageRefs": [
      8,
      9,
      10,
      11,
      12,
      13,
      14,
      15
    ]
  },
  {
    "contentKey": "d2d165647bd26528",
    "stock": 1106,
    "stockLevel": "in-stock",
    "price": 19.9,
    "color": {
      "name": "French Navy",
      "hex": "#12315a"
    },
    "size": "M",
    "imageRefs": [
      8,
      9,
      10,
      11,
      12,
      13,
      14,
      15
    ]
  },
  {
    "contentKey": "f132705a619d2228",
    "stock": 244,
    "stockLevel": "in-stock",
    "price": 19.9,
    "color": {
      "name": "Olive",
      "hex": "#6b6f58"
    },
    "size": "S",
    "imageRefs": [
      16,
      17,
      18,
      19,
      20,
      21,
      22,
      23
    ]
  },
  {
    "contentKey": "f30e690d6559687e",
    "stock": 2938,
    "stockLevel": "in-stock",
    "price": 19.9,
    "color": {
      "name": "Black",
      "hex": "#000000"
    },
    "size": "M",
    "imageRefs": [
      0,
      1,
      2,
      3,
      4,
      5,
      6,
      7
    ]
  },
  {
    "contentKey": "ff12522af43d6229",
    "stock": 2292,
    "stockLevel": "in-stock",
    "price": 19.9,
    "color": {
      "name": "Black",
      "hex": "#000000"
    },
    "size": "L",
    "imageRefs": [
      0,
      1,
      2,
      3,
      4,
      5,
      6,
      7
    ]
  }
]